ragstack_knowledge_store/__init__.py
ragstack_knowledge_store/_mmr_helper.py
ragstack_knowledge_store/_utils.py
ragstack_knowledge_store/concurrency.py
ragstack_knowledge_store/content.py
ragstack_knowledge_store/embedding_model.py
ragstack_knowledge_store/graph_store.py
ragstack_knowledge_store/knowledge_store.py
ragstack_knowledge_store/links.py
ragstack_knowledge_store/math.py
ragstack_ai_knowledge_store-0.2.0.dist-info/METADATA
ragstack_ai_knowledge_store-0.2.0.dist-info/WHEEL
ragstack_ai_knowledge_store-0.2.0.dist-info/RECORD
