Metadata-Version: 2.1
Name: ragstack-ai-knowledge-store
Version: 0.2.0
Summary: DataStax RAGStack Graph Store
Home-page: https://github.com/datastax/ragstack-ai
License: BUSL-1.1
Author: DataStax
Requires-Python: >=3.9,<3.13
Classifier: License :: Other/Proprietary License
Classifier: Programming Language :: Python :: 3
Classifier: Programming Language :: Python :: 3.9
Classifier: Programming Language :: Python :: 3.10
Classifier: Programming Language :: Python :: 3.11
Classifier: Programming Language :: Python :: 3.12
Requires-Dist: cassio (>=0.1.7,<0.2.0)
Project-URL: Documentation, https://docs.datastax.com/en/ragstack
Project-URL: Repository, https://github.com/datastax/ragstack-ai
